{"tournament":"2026 FIFA World Cup","stage":"Pre-tournament","completed":0,"results_through":null,"knockout_results":[],"groups":{"A":{"teams":[{"team":"Mexico","slug":"mexico","rating":1982.0,"elo_base":1980.0,"squad_index":73.4,"combined_index":80.1,"mp":0,"pts":0,"gd":0,"gf":0,"p_1st":61.2,"p_2nd":24.2,"p_3rd":11.4,"p_4th":3.2,"p_r32":95.1,"p_r16":65.4,"p_qf":29.6,"p_sf":12.3,"p_final":5.9,"p_winner":2.1},{"team":"South Korea","slug":"south-korea","rating":1867.0,"elo_base":1884.0,"squad_index":66.3,"combined_index":72.4,"mp":0,"pts":0,"gd":0,"gf":0,"p_1st":21.3,"p_2nd":36.5,"p_3rd":28.0,"p_4th":14.1,"p_r32":78.6,"p_r16":34.8,"p_qf":11.6,"p_sf":3.2,"p_final":1.0,"p_winner":0.1},{"team":"Czech Republic","slug":"czech-republic","rating":1807.0,"elo_base":1809.0,"squad_index":71.8,"combined_index":68.4,"mp":0,"pts":0,"gd":0,"gf":0,"p_1st":14.1,"p_2nd":29.0,"p_3rd":36.0,"p_4th":20.9,"p_r32":68.7,"p_r16":24.6,"p_qf":7.1,"p_sf":1.6,"p_final":0.4,"p_winner":0.1},{"team":"South Africa","slug":"south-africa","rating":1633.0,"elo_base":1671.0,"squad_index":58.2,"combined_index":56.6,"mp":0,"pts":0,"gd":0,"gf":0,"p_1st":3.3,"p_2nd":10.3,"p_3rd":24.6,"p_4th":61.8,"p_r32":28.1,"p_r16":5.5,"p_qf":1.1,"p_sf":0.2,"p_final":0.0,"p_winner":0.0}],"matches":[{"home":"Mexico","away":"South Africa","p_home":79.3,"p_draw":13.0,"p_away":7.7,"is_neutral":false,"date":"Jun 11","venue":"Mexico City"},{"home":"South Korea","away":"Czech Republic","p_home":45.2,"p_draw":23.1,"p_away":31.7,"is_neutral":true,"date":"Jun 11","venue":"Guadalajara"},{"home":"Czech Republic","away":"South Africa","p_home":58.7,"p_draw":20.4,"p_away":20.9,"is_neutral":true,"date":"Jun 18","venue":"Atlanta"},{"home":"Mexico","away":"South Korea","p_home":57.1,"p_draw":21.1,"p_away":21.8,"is_neutral":false,"date":"Jun 18","venue":"Guadalajara"},{"home":"Mexico","away":"Czech Republic","p_home":63.5,"p_draw":19.3,"p_away":17.3,"is_neutral":false,"date":"Jun 24","venue":"Mexico City"},{"home":"South Africa","away":"South Korea","p_home":15.8,"p_draw":18.6,"p_away":65.6,"is_neutral":true,"date":"Jun 24","venue":"Guadalajara"}]},"B":{"teams":[{"team":"Switzerland","slug":"switzerland","rating":1971.0,"elo_base":1957.0,"squad_index":78.0,"combined_index":79.4,"mp":0,"pts":0,"gd":0,"gf":0,"p_1st":50.5,"p_2nd":37.3,"p_3rd":10.1,"p_4th":2.1,"p_r32":96.3,"p_r16":58.9,"p_qf":19.8,"p_sf":8.1,"p_final":2.5,"p_winner":0.8},{"team":"Canada","slug":"canada","rating":1894.0,"elo_base":1902.0,"squad_index":69.5,"combined_index":74.2,"mp":0,"pts":0,"gd":0,"gf":0,"p_1st":43.3,"p_2nd":40.2,"p_3rd":13.4,"p_4th":3.1,"p_r32":94.6,"p_r16":52.6,"p_qf":17.0,"p_sf":6.6,"p_final":2.1,"p_winner":0.7},{"team":"Bosnia and Herzegovina","slug":"bosnia-and-herzegovina","rating":1644.0,"elo_base":1659.0,"squad_index":67.0,"combined_index":57.4,"mp":0,"pts":0,"gd":0,"gf":0,"p_1st":4.6,"p_2nd":15.6,"p_3rd":46.1,"p_4th":33.7,"p_r32":47.8,"p_r16":7.6,"p_qf":1.3,"p_sf":0.2,"p_final":0.0,"p_winner":0.0},{"team":"Qatar","slug":"qatar","rating":1535.0,"elo_base":1589.0,"squad_index":52.3,"combined_index":50.0,"mp":0,"pts":0,"gd":0,"gf":0,"p_1st":1.6,"p_2nd":6.8,"p_3rd":30.4,"p_4th":61.2,"p_r32":24.3,"p_r16":2.5,"p_qf":0.3,"p_sf":0.1,"p_final":0.0,"p_winner":0.0}],"matches":[{"home":"Canada","away":"Bosnia and Herzegovina","p_home":70.4,"p_draw":16.8,"p_away":12.8,"is_neutral":false,"date":"Jun 12","venue":"Toronto"},{"home":"Qatar","away":"Switzerland","p_home":5.8,"p_draw":11.0,"p_away":83.2,"is_neutral":true,"date":"Jun 13","venue":"Santa Clara"},{"home":"Switzerland","away":"Bosnia and Herzegovina","p_home":74.6,"p_draw":15.1,"p_away":10.3,"is_neutral":true,"date":"Jun 18","venue":"Inglewood"},{"home":"Canada","away":"Qatar","p_home":81.9,"p_draw":11.7,"p_away":6.4,"is_neutral":false,"date":"Jun 18","venue":"Vancouver"},{"home":"Canada","away":"Switzerland","p_home":34.5,"p_draw":23.3,"p_away":42.2,"is_neutral":false,"date":"Jun 24","venue":"Vancouver"},{"home":"Bosnia and Herzegovina","away":"Qatar","p_home":50.9,"p_draw":22.2,"p_away":26.9,"is_neutral":true,"date":"Jun 24","venue":"Seattle"}]},"C":{"teams":[{"team":"Brazil","slug":"brazil","rating":2112.0,"elo_base":2057.0,"squad_index":93.2,"combined_index":88.9,"mp":0,"pts":0,"gd":0,"gf":0,"p_1st":55.9,"p_2nd":30.5,"p_3rd":11.5,"p_4th":2.1,"p_r32":96.3,"p_r16":60.7,"p_qf":36.2,"p_sf":23.3,"p_final":11.7,"p_winner":5.2},{"team":"Morocco","slug":"morocco","rating":2026.0,"elo_base":1999.0,"squad_index":82.6,"combined_index":83.1,"mp":0,"pts":0,"gd":0,"gf":0,"p_1st":34.1,"p_2nd":41.2,"p_3rd":19.6,"p_4th":5.1,"p_r32":91.0,"p_r16":46.3,"p_qf":21.2,"p_sf":11.6,"p_final":4.9,"p_winner":1.6},{"team":"Scotland","slug":"scotland","rating":1842.0,"elo_base":1855.0,"squad_index":67.9,"combined_index":70.7,"mp":0,"pts":0,"gd":0,"gf":0,"p_1st":8.9,"p_2nd":22.6,"p_3rd":47.3,"p_4th":21.1,"p_r32":64.1,"p_r16":16.9,"p_qf":5.2,"p_sf":1.7,"p_final":0.5,"p_winner":0.1},{"team":"Haiti","slug":"haiti","rating":1640.0,"elo_base":1687.0,"squad_index":54.8,"combined_index":57.1,"mp":0,"pts":0,"gd":0,"gf":0,"p_1st":1.1,"p_2nd":5.7,"p_3rd":21.5,"p_4th":71.7,"p_r32":18.1,"p_r16":2.3,"p_qf":0.3,"p_sf":0.0,"p_final":0.0,"p_winner":0.0}],"matches":[{"home":"Brazil","away":"Morocco","p_home":50.1,"p_draw":22.5,"p_away":27.5,"is_neutral":true,"date":"Jun 13","venue":"East Rutherford"},{"home":"Haiti","away":"Scotland","p_home":17.6,"p_draw":19.6,"p_away":62.8,"is_neutral":true,"date":"Jun 13","venue":"Foxborough"},{"home":"Scotland","away":"Morocco","p_home":18.8,"p_draw":20.1,"p_away":61.1,"is_neutral":true,"date":"Jun 19","venue":"Foxborough"},{"home":"Brazil","away":"Haiti","p_home":85.8,"p_draw":9.6,"p_away":4.5,"is_neutral":true,"date":"Jun 19","venue":"Philadelphia"},{"home":"Scotland","away":"Brazil","p_home":14.7,"p_draw":17.8,"p_away":67.5,"is_neutral":true,"date":"Jun 24","venue":"Miami"},{"home":"Morocco","away":"Haiti","p_home":78.8,"p_draw":13.1,"p_away":8.1,"is_neutral":true,"date":"Jun 24","venue":"Atlanta"}]},"D":{"teams":[{"team":"Turkey","slug":"turkey","rating":1991.0,"elo_base":1970.0,"squad_index":80.4,"combined_index":80.7,"mp":0,"pts":0,"gd":0,"gf":0,"p_1st":39.0,"p_2nd":26.7,"p_3rd":20.2,"p_4th":14.1,"p_r32":81.8,"p_r16":52.1,"p_qf":26.9,"p_sf":8.6,"p_final":3.3,"p_winner":1.3},{"team":"United States","slug":"united-states","rating":1881.0,"elo_base":1864.0,"squad_index":78.7,"combined_index":73.3,"mp":0,"pts":0,"gd":0,"gf":0,"p_1st":25.1,"p_2nd":27.3,"p_3rd":25.0,"p_4th":22.6,"p_r32":71.1,"p_r16":40.0,"p_qf":17.3,"p_sf":4.9,"p_final":1.5,"p_winner":0.6},{"team":"Paraguay","slug":"paraguay","rating":1898.0,"elo_base":1907.0,"squad_index":69.0,"combined_index":74.4,"mp":0,"pts":0,"gd":0,"gf":0,"p_1st":19.8,"p_2nd":23.9,"p_3rd":26.9,"p_4th":29.3,"p_r32":63.7,"p_r16":33.5,"p_qf":13.4,"p_sf":3.6,"p_final":1.1,"p_winner":0.4},{"team":"Australia","slug":"australia","rating":1870.0,"elo_base":1904.0,"squad_index":60.0,"combined_index":72.6,"mp":0,"pts":0,"gd":0,"gf":0,"p_1st":16.0,"p_2nd":22.0,"p_3rd":27.9,"p_4th":34.0,"p_r32":57.9,"p_r16":27.9,"p_qf":10.6,"p_sf":2.5,"p_final":0.6,"p_winner":0.2}],"matches":[{"home":"United States","away":"Paraguay","p_home":41.4,"p_draw":23.5,"p_away":35.1,"is_neutral":false,"date":"Jun 12","venue":"Inglewood"},{"home":"Australia","away":"Turkey","p_home":25.2,"p_draw":22.2,"p_away":52.6,"is_neutral":true,"date":"Jun 13","venue":"Vancouver"},{"home":"United States","away":"Australia","p_home":44.5,"p_draw":23.4,"p_away":32.1,"is_neutral":false,"date":"Jun 19","venue":"Seattle"},{"home":"Turkey","away":"Paraguay","p_home":47.9,"p_draw":23.0,"p_away":29.1,"is_neutral":true,"date":"Jun 19","venue":"Santa Clara"},{"home":"United States","away":"Turkey","p_home":33.0,"p_draw":23.4,"p_away":43.6,"is_neutral":false,"date":"Jun 25","venue":"Inglewood"},{"home":"Paraguay","away":"Australia","p_home":40.2,"p_draw":23.7,"p_away":36.1,"is_neutral":true,"date":"Jun 25","venue":"Santa Clara"}]},"E":{"teams":[{"team":"Germany","slug":"germany","rating":2078.0,"elo_base":2019.0,"squad_index":94.6,"combined_index":86.6,"mp":0,"pts":0,"gd":0,"gf":0,"p_1st":52.5,"p_2nd":32.5,"p_3rd":13.3,"p_4th":1.7,"p_r32":96.6,"p_r16":67.4,"p_qf":43.0,"p_sf":21.4,"p_final":10.3,"p_winner":4.3},{"team":"Ecuador","slug":"ecuador","rating":2016.0,"elo_base":2017.0,"squad_index":72.3,"combined_index":82.4,"mp":0,"pts":0,"gd":0,"gf":0,"p_1st":36.7,"p_2nd":39.6,"p_3rd":20.5,"p_4th":3.2,"p_r32":93.8,"p_r16":55.1,"p_qf":29.8,"p_sf":13.2,"p_final":5.2,"p_winner":1.8},{"team":"Ivory Coast","slug":"ivory-coast","rating":1841.0,"elo_base":1817.0,"squad_index":81.7,"combined_index":70.7,"mp":0,"pts":0,"gd":0,"gf":0,"p_1st":10.4,"p_2nd":24.9,"p_3rd":50.2,"p_4th":14.4,"p_r32":71.6,"p_r16":22.9,"p_qf":8.1,"p_sf":2.1,"p_final":0.6,"p_winner":0.1},{"team":"Curacao","slug":"curacao","rating":1547.0,"elo_base":1600.0,"squad_index":52.5,"combined_index":50.8,"mp":0,"pts":0,"gd":0,"gf":0,"p_1st":0.4,"p_2nd":3.0,"p_3rd":15.9,"p_4th":80.7,"p_r32":10.9,"p_r16":1.1,"p_qf":0.2,"p_sf":0.0,"p_final":0.0,"p_winner":0.0}],"matches":[{"home":"Germany","away":"Curacao","p_home":89.7,"p_draw":7.3,"p_away":2.9,"is_neutral":true,"date":"Jun 14","venue":"Houston"},{"home":"Ivory Coast","away":"Ecuador","p_home":20.5,"p_draw":20.4,"p_away":59.1,"is_neutral":true,"date":"Jun 14","venue":"Philadelphia"},{"home":"Germany","away":"Ivory Coast","p_home":65.1,"p_draw":18.9,"p_away":16.1,"is_neutral":true,"date":"Jun 20","venue":"Toronto"},{"home":"Ecuador","away":"Curacao","p_home":86.4,"p_draw":9.1,"p_away":4.5,"is_neutral":true,"date":"Jun 20","venue":"Kansas City"},{"home":"Ecuador","away":"Germany","p_home":30.2,"p_draw":23.2,"p_away":46.6,"is_neutral":true,"date":"Jun 25","venue":"East Rutherford"},{"home":"Curacao","away":"Ivory Coast","p_home":11.9,"p_draw":16.3,"p_away":71.7,"is_neutral":true,"date":"Jun 25","venue":"Philadelphia"}]},"F":{"teams":[{"team":"Netherlands","slug":"netherlands","rating":2072.0,"elo_base":2018.0,"squad_index":92.8,"combined_index":86.2,"mp":0,"pts":0,"gd":0,"gf":0,"p_1st":53.5,"p_2nd":32.0,"p_3rd":11.2,"p_4th":3.3,"p_r32":94.8,"p_r16":52.8,"p_qf":28.1,"p_sf":16.3,"p_final":7.4,"p_winner":3.1},{"team":"Japan","slug":"japan","rating":2009.0,"elo_base":2001.0,"squad_index":75.6,"combined_index":81.9,"mp":0,"pts":0,"gd":0,"gf":0,"p_1st":36.2,"p_2nd":39.2,"p_3rd":18.0,"p_4th":6.6,"p_r32":89.9,"p_r16":40.0,"p_qf":17.9,"p_sf":9.8,"p_final":4.0,"p_winner":1.5},{"team":"Sweden","slug":"sweden","rating":1787.0,"elo_base":1776.0,"squad_index":76.6,"combined_index":67.0,"mp":0,"pts":0,"gd":0,"gf":0,"p_1st":7.4,"p_2nd":19.1,"p_3rd":40.5,"p_4th":32.9,"p_r32":52.8,"p_r16":11.6,"p_qf":3.3,"p_sf":0.8,"p_final":0.2,"p_winner":0.1},{"team":"Tunisia","slug":"tunisia","rating":1696.0,"elo_base":1731.0,"squad_index":59.6,"combined_index":60.9,"mp":0,"pts":0,"gd":0,"gf":0,"p_1st":2.8,"p_2nd":9.8,"p_3rd":30.2,"p_4th":57.2,"p_r32":29.7,"p_r16":4.6,"p_qf":0.9,"p_sf":0.1,"p_final":0.0,"p_winner":0.0}],"matches":[{"home":"Netherlands","away":"Japan","p_home":43.6,"p_draw":23.5,"p_away":32.8,"is_neutral":true,"date":"Jun 14","venue":"Arlington"},{"home":"Sweden","away":"Tunisia","p_home":49.2,"p_draw":22.7,"p_away":28.1,"is_neutral":true,"date":"Jun 14","venue":"Guadalajara"},{"home":"Netherlands","away":"Sweden","p_home":70.3,"p_draw":16.9,"p_away":12.8,"is_neutral":true,"date":"Jun 20","venue":"Houston"},{"home":"Tunisia","away":"Japan","p_home":11.2,"p_draw":16.0,"p_away":72.9,"is_neutral":true,"date":"Jun 20","venue":"Guadalajara"},{"home":"Japan","away":"Sweden","p_home":64.8,"p_draw":18.8,"p_away":16.4,"is_neutral":true,"date":"Jun 25","venue":"Arlington"},{"home":"Tunisia","away":"Netherlands","p_home":7.0,"p_draw":12.4,"p_away":80.6,"is_neutral":true,"date":"Jun 25","venue":"Kansas City"}]},"G":{"teams":[{"team":"Belgium","slug":"belgium","rating":1993.0,"elo_base":1953.0,"squad_index":87.6,"combined_index":80.9,"mp":0,"pts":0,"gd":0,"gf":0,"p_1st":56.0,"p_2nd":26.0,"p_3rd":12.8,"p_4th":5.2,"p_r32":92.6,"p_r16":57.4,"p_qf":28.9,"p_sf":8.9,"p_final":3.3,"p_winner":1.4},{"team":"Iran","slug":"iran","rating":1856.0,"elo_base":1898.0,"squad_index":56.8,"combined_index":71.6,"mp":0,"pts":0,"gd":0,"gf":0,"p_1st":23.6,"p_2nd":33.3,"p_3rd":26.4,"p_4th":16.7,"p_r32":76.4,"p_r16":32.5,"p_qf":11.1,"p_sf":2.2,"p_final":0.7,"p_winner":0.2},{"team":"Egypt","slug":"egypt","rating":1779.0,"elo_base":1807.0,"squad_index":62.1,"combined_index":66.4,"mp":0,"pts":0,"gd":0,"gf":0,"p_1st":14.0,"p_2nd":24.7,"p_3rd":33.1,"p_4th":28.3,"p_r32":61.9,"p_r16":20.1,"p_qf":5.3,"p_sf":0.8,"p_final":0.2,"p_winner":0.1},{"team":"New Zealand","slug":"new-zealand","rating":1687.0,"elo_base":1733.0,"squad_index":55.2,"combined_index":60.2,"mp":0,"pts":0,"gd":0,"gf":0,"p_1st":6.4,"p_2nd":16.0,"p_3rd":27.7,"p_4th":49.8,"p_r32":40.1,"p_r16":9.6,"p_qf":2.0,"p_sf":0.2,"p_final":0.0,"p_winner":0.0}],"matches":[{"home":"Belgium","away":"Egypt","p_home":63.5,"p_draw":19.1,"p_away":17.4,"is_neutral":true,"date":"Jun 15","venue":"Seattle"},{"home":"Iran","away":"New Zealand","p_home":56.8,"p_draw":21.1,"p_away":22.1,"is_neutral":true,"date":"Jun 15","venue":"Inglewood"},{"home":"Belgium","away":"Iran","p_home":53.3,"p_draw":22.2,"p_away":24.6,"is_neutral":true,"date":"Jun 21","venue":"Inglewood"},{"home":"New Zealand","away":"Egypt","p_home":28.2,"p_draw":23.2,"p_away":48.6,"is_neutral":true,"date":"Jun 21","venue":"Vancouver"},{"home":"Egypt","away":"Iran","p_home":29.4,"p_draw":23.2,"p_away":47.4,"is_neutral":true,"date":"Jun 26","venue":"Seattle"},{"home":"New Zealand","away":"Belgium","p_home":10.6,"p_draw":15.4,"p_away":74.0,"is_neutral":true,"date":"Jun 26","venue":"Vancouver"}]},"H":{"teams":[{"team":"Spain","slug":"spain","rating":2277.0,"elo_base":2212.0,"squad_index":97.0,"combined_index":100.0,"mp":0,"pts":0,"gd":0,"gf":0,"p_1st":83.5,"p_2nd":15.3,"p_3rd":1.1,"p_4th":0.1,"p_r32":99.8,"p_r16":81.5,"p_qf":65.1,"p_sf":53.2,"p_final":35.7,"p_winner":24.2},{"team":"Uruguay","slug":"uruguay","rating":1979.0,"elo_base":1964.0,"squad_index":77.9,"combined_index":79.9,"mp":0,"pts":0,"gd":0,"gf":0,"p_1st":15.5,"p_2nd":66.2,"p_3rd":14.5,"p_4th":3.8,"p_r32":92.0,"p_r16":29.8,"p_qf":15.8,"p_sf":7.2,"p_final":2.3,"p_winner":0.9},{"team":"Saudi Arabia","slug":"saudi-arabia","rating":1657.0,"elo_base":1701.0,"squad_index":55.8,"combined_index":58.2,"mp":0,"pts":0,"gd":0,"gf":0,"p_1st":0.6,"p_2nd":11.2,"p_3rd":47.0,"p_4th":41.1,"p_r32":32.6,"p_r16":4.3,"p_qf":1.1,"p_sf":0.1,"p_final":0.0,"p_winner":0.0},{"team":"Cape Verde","slug":"cape-verde","rating":1605.0,"elo_base":1646.0,"squad_index":57.0,"combined_index":54.7,"mp":0,"pts":0,"gd":0,"gf":0,"p_1st":0.4,"p_2nd":7.3,"p_3rd":37.3,"p_4th":55.0,"p_r32":23.4,"p_r16":2.7,"p_qf":0.5,"p_sf":0.1,"p_final":0.0,"p_winner":0.0}],"matches":[{"home":"Spain","away":"Cape Verde","p_home":94.6,"p_draw":4.1,"p_away":1.3,"is_neutral":true,"date":"Jun 15","venue":"Atlanta"},{"home":"Saudi Arabia","away":"Uruguay","p_home":10.9,"p_draw":15.7,"p_away":73.5,"is_neutral":true,"date":"Jun 15","venue":"Miami"},{"home":"Spain","away":"Saudi Arabia","p_home":93.6,"p_draw":4.8,"p_away":1.5,"is_neutral":true,"date":"Jun 21","venue":"Atlanta"},{"home":"Uruguay","away":"Cape Verde","p_home":78.6,"p_draw":13.4,"p_away":8.0,"is_neutral":true,"date":"Jun 21","venue":"Miami"},{"home":"Cape Verde","away":"Saudi Arabia","p_home":30.3,"p_draw":23.2,"p_away":46.5,"is_neutral":true,"date":"Jun 26","venue":"Houston"},{"home":"Uruguay","away":"Spain","p_home":12.5,"p_draw":17.1,"p_away":70.4,"is_neutral":true,"date":"Jun 26","venue":"Guadalajara"}]},"I":{"teams":[{"team":"France","slug":"france","rating":2194.0,"elo_base":2120.0,"squad_index":100.0,"combined_index":94.4,"mp":0,"pts":0,"gd":0,"gf":0,"p_1st":66.3,"p_2nd":23.8,"p_3rd":8.4,"p_4th":1.5,"p_r32":97.4,"p_r16":81.4,"p_qf":59.3,"p_sf":37.5,"p_final":24.3,"p_winner":12.2},{"team":"Norway","slug":"norway","rating":2001.0,"elo_base":1978.0,"squad_index":81.4,"combined_index":81.4,"mp":0,"pts":0,"gd":0,"gf":0,"p_1st":20.4,"p_2nd":39.9,"p_3rd":30.4,"p_4th":9.3,"p_r32":83.5,"p_r16":48.7,"p_qf":19.4,"p_sf":8.0,"p_final":3.6,"p_winner":1.4},{"team":"Senegal","slug":"senegal","rating":1928.0,"elo_base":1902.0,"squad_index":82.1,"combined_index":76.5,"mp":0,"pts":0,"gd":0,"gf":0,"p_1st":12.2,"p_2nd":30.0,"p_3rd":41.1,"p_4th":16.7,"p_r32":71.5,"p_r16":35.0,"p_qf":12.2,"p_sf":4.1,"p_final":1.5,"p_winner":0.6},{"team":"Iraq","slug":"iraq","rating":1683.0,"elo_base":1740.0,"squad_index":51.3,"combined_index":60.0,"mp":0,"pts":0,"gd":0,"gf":0,"p_1st":1.2,"p_2nd":6.3,"p_3rd":20.2,"p_4th":72.4,"p_r32":17.7,"p_r16":4.2,"p_qf":0.8,"p_sf":0.1,"p_final":0.0,"p_winner":0.0}],"matches":[{"home":"France","away":"Senegal","p_home":68.6,"p_draw":17.6,"p_away":13.8,"is_neutral":true,"date":"Jun 16","venue":"East Rutherford"},{"home":"Iraq","away":"Norway","p_home":10.4,"p_draw":15.3,"p_away":74.3,"is_neutral":true,"date":"Jun 16","venue":"Foxborough"},{"home":"France","away":"Iraq","p_home":87.7,"p_draw":8.5,"p_away":3.8,"is_neutral":true,"date":"Jun 22","venue":"Philadelphia"},{"home":"Norway","away":"Senegal","p_home":45.5,"p_draw":23.2,"p_away":31.3,"is_neutral":true,"date":"Jun 22","venue":"East Rutherford"},{"home":"Norway","away":"France","p_home":19.2,"p_draw":20.5,"p_away":60.2,"is_neutral":true,"date":"Jun 26","venue":"Foxborough"},{"home":"Senegal","away":"Iraq","p_home":66.1,"p_draw":18.5,"p_away":15.4,"is_neutral":true,"date":"Jun 26","venue":"Toronto"}]},"J":{"teams":[{"team":"Argentina","slug":"argentina","rating":2231.0,"elo_base":2182.0,"squad_index":90.9,"combined_index":96.9,"mp":0,"pts":0,"gd":0,"gf":0,"p_1st":80.9,"p_2nd":14.4,"p_3rd":4.0,"p_4th":0.7,"p_r32":98.8,"p_r16":73.3,"p_qf":58.7,"p_sf":43.1,"p_final":25.9,"p_winner":16.6},{"team":"Austria","slug":"austria","rating":1902.0,"elo_base":1894.0,"squad_index":75.2,"combined_index":74.7,"mp":0,"pts":0,"gd":0,"gf":0,"p_1st":9.9,"p_2nd":40.2,"p_3rd":31.9,"p_4th":18.0,"p_r32":71.7,"p_r16":19.1,"p_qf":7.5,"p_sf":2.9,"p_final":0.9,"p_winner":0.3},{"team":"Algeria","slug":"algeria","rating":1868.0,"elo_base":1869.0,"squad_index":72.2,"combined_index":72.4,"mp":0,"pts":0,"gd":0,"gf":0,"p_1st":7.4,"p_2nd":33.2,"p_3rd":36.5,"p_4th":22.9,"p_r32":64.3,"p_r16":15.8,"p_qf":5.9,"p_sf":2.1,"p_final":0.5,"p_winner":0.1},{"team":"Jordan","slug":"jordan","rating":1713.0,"elo_base":1773.0,"squad_index":50.0,"combined_index":62.0,"mp":0,"pts":0,"gd":0,"gf":0,"p_1st":1.8,"p_2nd":12.2,"p_3rd":27.5,"p_4th":58.5,"p_r32":28.2,"p_r16":4.4,"p_qf":1.0,"p_sf":0.2,"p_final":0.0,"p_winner":0.0}],"matches":[{"home":"Argentina","away":"Algeria","p_home":77.7,"p_draw":13.6,"p_away":8.7,"is_neutral":true,"date":"Jun 16","venue":"Kansas City"},{"home":"Austria","away":"Jordan","p_home":60.8,"p_draw":20.2,"p_away":18.9,"is_neutral":true,"date":"Jun 16","venue":"Santa Clara"},{"home":"Argentina","away":"Austria","p_home":75.2,"p_draw":14.9,"p_away":9.9,"is_neutral":true,"date":"Jun 22","venue":"Arlington"},{"home":"Jordan","away":"Algeria","p_home":21.4,"p_draw":20.9,"p_away":57.7,"is_neutral":true,"date":"Jun 22","venue":"Santa Clara"},{"home":"Algeria","away":"Austria","p_home":35.3,"p_draw":23.1,"p_away":41.6,"is_neutral":true,"date":"Jun 27","venue":"Kansas City"},{"home":"Jordan","away":"Argentina","p_home":3.0,"p_draw":7.5,"p_away":89.4,"is_neutral":true,"date":"Jun 27","venue":"Arlington"}]},"K":{"teams":[{"team":"Portugal","slug":"portugal","rating":2096.0,"elo_base":2038.0,"squad_index":94.2,"combined_index":87.8,"mp":0,"pts":0,"gd":0,"gf":0,"p_1st":49.9,"p_2nd":35.0,"p_3rd":11.2,"p_4th":3.9,"p_r32":94.2,"p_r16":67.7,"p_qf":40.9,"p_sf":20.6,"p_final":9.2,"p_winner":4.7},{"team":"Colombia","slug":"colombia","rating":2065.0,"elo_base":2054.0,"squad_index":76.6,"combined_index":85.7,"mp":0,"pts":0,"gd":0,"gf":0,"p_1st":41.5,"p_2nd":38.6,"p_3rd":14.9,"p_4th":4.9,"p_r32":92.2,"p_r16":62.0,"p_qf":34.2,"p_sf":16.4,"p_final":6.9,"p_winner":3.4},{"team":"Uzbekistan","slug":"uzbekistan","rating":1788.0,"elo_base":1828.0,"squad_index":57.6,"combined_index":67.1,"mp":0,"pts":0,"gd":0,"gf":0,"p_1st":5.3,"p_2nd":15.8,"p_3rd":40.9,"p_4th":38.1,"p_r32":46.7,"p_r16":13.7,"p_qf":3.4,"p_sf":0.9,"p_final":0.2,"p_winner":0.1},{"team":"DR Congo","slug":"dr-congo","rating":1737.0,"elo_base":1756.0,"squad_index":65.3,"combined_index":63.6,"mp":0,"pts":0,"gd":0,"gf":0,"p_1st":3.3,"p_2nd":10.5,"p_3rd":33.1,"p_4th":53.1,"p_r32":32.8,"p_r16":8.9,"p_qf":2.0,"p_sf":0.5,"p_final":0.1,"p_winner":0.0}],"matches":[{"home":"Portugal","away":"DR Congo","p_home":76.5,"p_draw":14.4,"p_away":9.1,"is_neutral":true,"date":"Jun 17","venue":"Houston"},{"home":"Uzbekistan","away":"Colombia","p_home":13.8,"p_draw":17.8,"p_away":68.5,"is_neutral":true,"date":"Jun 17","venue":"Mexico City"},{"home":"Portugal","away":"Uzbekistan","p_home":71.9,"p_draw":16.5,"p_away":11.6,"is_neutral":true,"date":"Jun 23","venue":"Houston"},{"home":"Colombia","away":"DR Congo","p_home":75.1,"p_draw":15.1,"p_away":9.8,"is_neutral":true,"date":"Jun 23","venue":"Guadalajara"},{"home":"Colombia","away":"Portugal","p_home":34.2,"p_draw":23.7,"p_away":42.1,"is_neutral":true,"date":"Jun 27","venue":"Miami"},{"home":"DR Congo","away":"Uzbekistan","p_home":33.3,"p_draw":23.3,"p_away":43.4,"is_neutral":true,"date":"Jun 27","venue":"Atlanta"}]},"L":{"teams":[{"team":"England","slug":"england","rating":2157.0,"elo_base":2086.0,"squad_index":99.2,"combined_index":91.9,"mp":0,"pts":0,"gd":0,"gf":0,"p_1st":68.1,"p_2nd":24.9,"p_3rd":6.1,"p_4th":1.0,"p_r32":98.2,"p_r16":77.0,"p_qf":51.2,"p_sf":29.4,"p_final":17.8,"p_winner":8.9},{"team":"Croatia","slug":"croatia","rating":1989.0,"elo_base":1968.0,"squad_index":80.2,"combined_index":80.6,"mp":0,"pts":0,"gd":0,"gf":0,"p_1st":25.5,"p_2nd":48.7,"p_3rd":20.7,"p_4th":5.1,"p_r32":90.1,"p_r16":46.9,"p_qf":19.4,"p_sf":8.2,"p_final":3.4,"p_winner":1.1},{"team":"Panama","slug":"panama","rating":1795.0,"elo_base":1842.0,"squad_index":54.7,"combined_index":67.5,"mp":0,"pts":0,"gd":0,"gf":0,"p_1st":5.7,"p_2nd":20.9,"p_3rd":49.4,"p_4th":23.9,"p_r32":58.1,"p_r16":14.4,"p_qf":4.1,"p_sf":1.0,"p_final":0.2,"p_winner":0.1},{"team":"Ghana","slug":"ghana","rating":1615.0,"elo_base":1622.0,"squad_index":70.0,"combined_index":55.4,"mp":0,"pts":0,"gd":0,"gf":0,"p_1st":0.7,"p_2nd":5.5,"p_3rd":23.8,"p_4th":70.0,"p_r32":17.8,"p_r16":2.2,"p_qf":0.3,"p_sf":0.1,"p_final":0.0,"p_winner":0.0}],"matches":[{"home":"England","away":"Croatia","p_home":57.3,"p_draw":21.2,"p_away":21.5,"is_neutral":true,"date":"Jun 17","venue":"Arlington"},{"home":"Ghana","away":"Panama","p_home":20.0,"p_draw":20.4,"p_away":59.6,"is_neutral":true,"date":"Jun 17","venue":"Toronto"},{"home":"England","away":"Ghana","p_home":88.9,"p_draw":7.8,"p_away":3.3,"is_neutral":true,"date":"Jun 23","venue":"Foxborough"},{"home":"Panama","away":"Croatia","p_home":19.2,"p_draw":20.4,"p_away":60.4,"is_neutral":true,"date":"Jun 23","venue":"Toronto"},{"home":"Panama","away":"England","p_home":8.4,"p_draw":13.7,"p_away":77.9,"is_neutral":true,"date":"Jun 27","venue":"East Rutherford"},{"home":"Croatia","away":"Ghana","p_home":78.6,"p_draw":13.3,"p_away":8.1,"is_neutral":true,"date":"Jun 27","venue":"Philadelphia"}]}}}